nutui.py
app/__init__.py
app/blueprints/__init__.py
app/blueprints/api.py
app/blueprints/ui.py
app/data/__init__.py
app/helpers/__init__.py
app/helpers/convert.py
app/models/__init__.py
app/models/config.py
app/models/data.py
app/models/ui.py
app/models/users.py
app/static/__init__.py
app/static/css/__init__.py
app/static/js/__init__.py
app/templates/__init__.py
nutui-0.1.8.dist-info/LICENSE
nutui-0.1.8.dist-info/METADATA
nutui-0.1.8.dist-info/WHEEL
nutui-0.1.8.dist-info/entry_points.txt
nutui-0.1.8.dist-info/top_level.txt
nutui-0.1.8.dist-info/RECORD
