Metadata-Version: 2.1
Name: nutui
Version: 0.1.8
Summary: Nut Web UI using Flask
Home-page: https://github.com/beardedtek-com/nutui
Author: The Bearded Tek
Author-email: kenny@beardedtek.com
License: AGPLv3
Project-URL: Bug Tracker, https://github.com/beardedtek-com/nutui/issues
Project-URL: Funding, https://github.com/sponsors/BeardedTek-com
Project-URL: Source, https://github.com/beardedtek-com/nutui/
Keywords: ups,nut-server,nutd,nut,battery-backup,apc,cyberpower,tripp-lite
Classifier: Environment :: Web Environment
Classifier: License :: OSI Approved :: GNU Affero General Public License v3 or later (AGPLv3+)
Classifier: Topic :: System :: Power (UPS)
Classifier: Topic :: Utilities
Classifier: Development Status :: 3 - Alpha
Classifier: Framework :: Flask
Classifier: Intended Audience :: End Users/Desktop
Classifier: Intended Audience :: Information Technology
Classifier: Intended Audience :: System Administrators
Requires-Python: >=3.6, <4
License-File: LICENSE
Requires-Dist: nut2
Requires-Dist: Flask
Requires-Dist: flask-sqlalchemy
Requires-Dist: pytz
Requires-Dist: PyYAML
Requires-Dist: requests
